LICENSE
README.md
pyproject.toml
setup.py
examples/__init__.py
examples/macros/__init__.py
makrell/__init__.py
makrell/__main__.py
makrell/_mron_py.py
makrell/ast.py
makrell/baseformat.py
makrell/cli.py
makrell/io.py
makrell/mrml.py
makrell/mron.mr
makrell/parsing.py
makrell/tokeniser.py
makrell.egg-info/PKG-INFO
makrell.egg-info/SOURCES.txt
makrell.egg-info/dependency_links.txt
makrell.egg-info/entry_points.txt
makrell.egg-info/top_level.txt
makrell/langserver/__init__.py
makrell/makrellpy/__init__.py
makrell/makrellpy/_compile.py
makrell/makrellpy/_compile_binop.py
makrell/makrellpy/_compile_curly_reserved.py
makrell/makrellpy/_compiler_common.py
makrell/makrellpy/compiler.py
makrell/makrellpy/core.mrpy
makrell/makrellpy/patmatch.mrpy
makrell/makrellpy/py_primitives.py
makrell/makrellpy/pyast_builder.py
makrell/makrellpy/repl.mr
makrell/makrellpy/stdmetas.py
tests/test_mrml.py
tests/test_mron.py
tests/test_parsing.py
tests/test_tokeniser.py